pyCoreRelator/__init__.py
pyCoreRelator/analysis/__init__.py
pyCoreRelator/analysis/age_models.py
pyCoreRelator/analysis/diagnostics.py
pyCoreRelator/analysis/dtw_core.py
pyCoreRelator/analysis/path_combining.py
pyCoreRelator/analysis/path_finding.py
pyCoreRelator/analysis/path_helpers.py
pyCoreRelator/analysis/quality.py
pyCoreRelator/analysis/segments.py
pyCoreRelator/analysis/syn_strat.py
pyCoreRelator/analysis/syn_strat_plot.py
pyCoreRelator/preprocessing/__init__.py
pyCoreRelator/preprocessing/ct_plotting.py
pyCoreRelator/preprocessing/ct_processing.py
pyCoreRelator/preprocessing/datum_picker.py
pyCoreRelator/preprocessing/gap_filling.py
pyCoreRelator/preprocessing/gap_filling_plots.py
pyCoreRelator/preprocessing/rgb_plotting.py
pyCoreRelator/preprocessing/rgb_processing.py
pyCoreRelator/utils/__init__.py
pyCoreRelator/utils/animation.py
pyCoreRelator/utils/data_loader.py
pyCoreRelator/utils/helpers.py
pyCoreRelator/utils/matrix_plots.py
pyCoreRelator/utils/path_processing.py
pyCoreRelator/utils/plotting.py
pycorerelator-0.0.2.dist-info/licenses/LICENSE
pycorerelator-0.0.2.dist-info/METADATA
pycorerelator-0.0.2.dist-info/WHEEL
pycorerelator-0.0.2.dist-info/top_level.txt
pycorerelator-0.0.2.dist-info/RECORD
