Metadata-Version: 2.4
Name: pycorerelator
Version: 0.0.2
Summary: A package for quantitative stratigraphic correlation across geological core and physical log data
Home-page: https://github.com/GeoLarryLai/pyCoreRelator
Author: Larry Syu-Heng Lai
Author-email: Larry Syu-Heng Lai <larrysyuhenglai@gmail.com>
License-Expression: AGPL-3.0-or-later
Project-URL: Homepage, https://github.com/GeoLarryLai/pyCoreRelator
Project-URL: Repository, https://github.com/GeoLarryLai/pyCoreRelator.git
Classifier: Programming Language :: Python :: 3
Classifier: Operating System :: OS Independent
Requires-Python: >=3.9,<3.14
License-File: LICENSE
Requires-Dist: numpy>=1.20.0
Requires-Dist: pandas>=1.3.0
Requires-Dist: scipy>=1.7.0
Requires-Dist: matplotlib>=3.5.0
Requires-Dist: Pillow>=8.3.0
Requires-Dist: imageio>=2.9.0
Requires-Dist: librosa>=0.9.0
Requires-Dist: tqdm>=4.60.0
Requires-Dist: joblib>=1.1.0
Requires-Dist: IPython>=7.25.0
Requires-Dist: psutil>=5.8.0
Requires-Dist: pydicom>=2.3.0
Requires-Dist: opencv-python>=4.5.0
Requires-Dist: scikit-learn>=1.0.0
Requires-Dist: xgboost>=1.6.0
Requires-Dist: lightgbm>=3.3.0
Provides-Extra: interactive
Requires-Dist: ipympl>=0.9.0; extra == "interactive"
Provides-Extra: advanced
Requires-Dist: scikit-image>=0.18.0; extra == "advanced"
Dynamic: author
Dynamic: home-page
Dynamic: license-file
Dynamic: requires-python
